pyfedcamp/__init__.py
pyfedcamp/cli.py
pyfedcamp/placards.py
pyfedcamp/reservations.py
pyfedcamp/static/NPS_logo.png
pyfedcamp/static/__init__.py
pyfedcamp-0.1.0.dist-info/LICENSE
pyfedcamp-0.1.0.dist-info/METADATA
pyfedcamp-0.1.0.dist-info/WHEEL
pyfedcamp-0.1.0.dist-info/entry_points.txt
pyfedcamp-0.1.0.dist-info/RECORD
