Metadata-Version: 2.1
Name: pyfedcamp
Version: 0.1.0
Summary: Python client with tools for working with recreation.gov data.
License: MIT
Author: Sky Bristol
Author-email: skybristol@gmail.com
Requires-Python: >=3.10,<4.0
Classifier: License :: OSI Approved :: MIT License
Classifier: Programming Language :: Python :: 3
Classifier: Programming Language :: Python :: 3.10
Classifier: Programming Language :: Python :: 3.11
Classifier: Programming Language :: Python :: 3.12
Requires-Dist: importlib-resources (>=6.5.2,<7.0.0)
Requires-Dist: openpyxl (>=3.1.5,<4.0.0)
Requires-Dist: pandas (>=2.3.0,<3.0.0)
Requires-Dist: python-dateutil (>=2.9.0.post0,<3.0.0)
Requires-Dist: reportlab (>=4.4.1,<5.0.0)
